lim/__init__.py
lim/__main__.py
lim/about.py
lim/ctu/__init__.py
lim/ctu/get.py
lim/ctu/list.py
lim/ctu/overview.py
lim/ctu/show.py
lim/ctu/stats.py
lim/packet_cafe/README.md
lim/packet_cafe/__init__.py
lim/packet_cafe/about.py
lim/packet_cafe/ui.py
lim/packet_cafe/admin/__init__.py
lim/packet_cafe/admin/delete.py
lim/packet_cafe/admin/endpoints.py
lim/packet_cafe/admin/files.py
lim/packet_cafe/admin/info.py
lim/packet_cafe/admin/results.py
lim/packet_cafe/admin/sessions.py
lim/packet_cafe/api/__init__.py
lim/packet_cafe/api/endpoints.py
lim/packet_cafe/api/info.py
lim/packet_cafe/api/raw.py
lim/packet_cafe/api/requests.py
lim/packet_cafe/api/results.py
lim/packet_cafe/api/status.py
lim/packet_cafe/api/stop.py
lim/packet_cafe/api/tools.py
lim/packet_cafe/api/upload.py
lim/packet_cafe/extensions/__init__.py
lim/packet_cafe/extensions/docker_cmds.py
lim/packet_cafe/extensions/report.py
lim/pcap/__init__.py
lim/pcap/extract.py
lim/pcap/shift.py
lim/utils/__init__.py
lim_cli-21.2.7.dist-info/AUTHORS.rst
lim_cli-21.2.7.dist-info/LICENSE-2.0.txt
lim_cli-21.2.7.dist-info/METADATA
lim_cli-21.2.7.dist-info/WHEEL
lim_cli-21.2.7.dist-info/entry_points.txt
lim_cli-21.2.7.dist-info/namespace_packages.txt
lim_cli-21.2.7.dist-info/top_level.txt
lim_cli-21.2.7.dist-info/RECORD
