Metadata-Version: 2.1
Name: lim-cli
Version: 21.2.7
Summary: LiminalInfo command line app.
Home-page: https://github.com/davedittrich/lim-cli
Author: Dave Dittrich
Author-email: dave.dittrich@gmail.com
License: Apache Software License
Download-URL: https://github.com/davedittrich/lim-cli/tarball/master
Keywords: lim
Platform: UNKNOWN
Classifier: Development Status :: 4 - Beta
Classifier: Intended Audience :: Information Technology
Classifier: Intended Audience :: Science/Research
Classifier: Intended Audience :: Other Audience
Classifier: License :: OSI Approved :: Apache Software License
Classifier: Natural Language :: English
Classifier: Operating System :: OS Independent
Classifier: Programming Language :: Python :: 3
Classifier: Programming Language :: Python :: 3.6
Classifier: Programming Language :: Python :: 3.7
Classifier: Programming Language :: Python :: 3.8
Classifier: Topic :: Security
Classifier: Topic :: Utilities
Requires-Python: >=3.6.0
Requires-Dist: aiohttp
Requires-Dist: arrow (>=0.15.6)
Requires-Dist: bullet
Requires-Dist: docker
Requires-Dist: dpkt
Requires-Dist: beautifulsoup4
Requires-Dist: cliff
Requires-Dist: future
Requires-Dist: gitpython
Requires-Dist: pandas
Requires-Dist: python-secrets
Requires-Dist: pyreadline
Requires-Dist: setuptools (>=42)
Requires-Dist: setuptools-scm
Requires-Dist: six
Requires-Dist: requests (>=2.17.0)
